flightcoder/__init__.py
flightcoder/linear.py
flightcoder-0.0.2.dist-info/LICENSE
flightcoder-0.0.2.dist-info/METADATA
flightcoder-0.0.2.dist-info/WHEEL
flightcoder-0.0.2.dist-info/top_level.txt
flightcoder-0.0.2.dist-info/RECORD
