Metadata-Version: 2.1
Name: flightcoder
Version: 0.0.2
Summary: flight simulator
Home-page: UNKNOWN
Author: richard
Author-email: UNKNOWN
License: MIT License
